odoo/addons/hr_entry_type/__init__.py
odoo/addons/hr_entry_type/__manifest__.py
odoo/addons/hr_entry_type/models/__init__.py
odoo/addons/hr_entry_type/models/hr_entry_type.py
odoo/addons/hr_entry_type/security/ir.model.access.csv
odoo/addons/hr_entry_type/views/hr_entry_type_views.xml
odoo14_addon_hr_entry_type-14.0.2.0.0.dist-info/METADATA
odoo14_addon_hr_entry_type-14.0.2.0.0.dist-info/WHEEL
odoo14_addon_hr_entry_type-14.0.2.0.0.dist-info/top_level.txt
odoo14_addon_hr_entry_type-14.0.2.0.0.dist-info/RECORD
